datapro/__init__.py
datapro/dataPro.py
datapro/prefixNode.py
datapro/treeType.py
datapro_learning-1.0.dist-info/LICENSE
datapro_learning-1.0.dist-info/METADATA
datapro_learning-1.0.dist-info/WHEEL
datapro_learning-1.0.dist-info/top_level.txt
datapro_learning-1.0.dist-info/RECORD
