Metadata-Version: 2.1
Name: datapro-learning
Version: 1.0
Summary: learning common data structure
License-File: LICENSE
Requires-Dist: pandas
Requires-Dist: numpy
Requires-Dist: pythainlp
Requires-Dist: scipy
Requires-Dist: openpyxl
